odoo9_addon_sale_delivery_rate-9.0.1.0.0-py2.7-nspkg.pth
odoo9_addon_sale_delivery_rate-9.0.1.0.0.dist-info/DESCRIPTION.rst
odoo9_addon_sale_delivery_rate-9.0.1.0.0.dist-info/METADATA
odoo9_addon_sale_delivery_rate-9.0.1.0.0.dist-info/RECORD
odoo9_addon_sale_delivery_rate-9.0.1.0.0.dist-info/WHEEL
odoo9_addon_sale_delivery_rate-9.0.1.0.0.dist-info/metadata.json
odoo9_addon_sale_delivery_rate-9.0.1.0.0.dist-info/namespace_packages.txt
odoo9_addon_sale_delivery_rate-9.0.1.0.0.dist-info/top_level.txt
odoo_addons/sale_delivery_rate/README.rst
odoo_addons/sale_delivery_rate/__init__.py
odoo_addons/sale_delivery_rate/__openerp__.py
odoo_addons/sale_delivery_rate/demo/delivery_carrier.xml
odoo_addons/sale_delivery_rate/demo/delivery_carrier_rate.xml
odoo_addons/sale_delivery_rate/demo/product_product.xml
odoo_addons/sale_delivery_rate/demo/product_template.xml
odoo_addons/sale_delivery_rate/demo/res_partner.xml
odoo_addons/sale_delivery_rate/demo/sale_order.xml
odoo_addons/sale_delivery_rate/demo/sale_order_line.xml
odoo_addons/sale_delivery_rate/demo/stock_picking.xml
odoo_addons/sale_delivery_rate/demo/stock_picking_rate.xml
odoo_addons/sale_delivery_rate/models/__init__.py
odoo_addons/sale_delivery_rate/models/delivery_carrier.py
odoo_addons/sale_delivery_rate/models/delivery_carrier_rate.py
odoo_addons/sale_delivery_rate/models/sale_order.py
odoo_addons/sale_delivery_rate/models/stock_move.py
odoo_addons/sale_delivery_rate/security/ir.model.access.csv
odoo_addons/sale_delivery_rate/static/description/icon.png
odoo_addons/sale_delivery_rate/tests/__init__.py
odoo_addons/sale_delivery_rate/tests/test_delivery_carrier.py
odoo_addons/sale_delivery_rate/tests/test_delivery_carrier_rate.py
odoo_addons/sale_delivery_rate/tests/test_stock_move.py
